LICENSE
MANIFEST.in
README.md
requirements.txt
setup.py
filez/__init__.py
filez/excel_parser.py
filez/html_parser.py
filez/ini_parser.py
filez/json_encoder.py
filez/pem_parser.py
filez/properties_parser.py
filez/utils.py
filez/vcard3_parser.py
filez/xml_parser.py
filez/yaml_loader.py
filez.egg-info/PKG-INFO
filez.egg-info/SOURCES.txt
filez.egg-info/dependency_links.txt
filez.egg-info/top_level.txt
filez.egg-info/zip-safe
tests/test_filez.py
tests/test_utils.py