Metadata-Version: 2.4
Name: filez
Version: 0.15
Summary: Easy use for fetch data from kinds of files
Home-page: https://github.com/hanzhichao/filez
Author: Han Zhichao
Author-email: superhin@126.com
License: MIT license
Keywords: filez,email,attachments
Classifier: Programming Language :: Python
Classifier: Programming Language :: Python :: 3.7
License-File: LICENSE
Dynamic: author
Dynamic: author-email
Dynamic: classifier
Dynamic: description
Dynamic: description-content-type
Dynamic: home-page
Dynamic: keywords
Dynamic: license
Dynamic: license-file
Dynamic: summary
